azure/mgmt/hybridnetwork/__init__.py
azure/mgmt/hybridnetwork/_configuration.py
azure/mgmt/hybridnetwork/_hybrid_network_management_client.py
azure/mgmt/hybridnetwork/_patch.py
azure/mgmt/hybridnetwork/_serialization.py
azure/mgmt/hybridnetwork/_vendor.py
azure/mgmt/hybridnetwork/_version.py
azure/mgmt/hybridnetwork/py.typed
azure/mgmt/hybridnetwork/aio/__init__.py
azure/mgmt/hybridnetwork/aio/_configuration.py
azure/mgmt/hybridnetwork/aio/_hybrid_network_management_client.py
azure/mgmt/hybridnetwork/aio/_patch.py
azure/mgmt/hybridnetwork/aio/operations/__init__.py
azure/mgmt/hybridnetwork/aio/operations/_artifact_manifests_operations.py
azure/mgmt/hybridnetwork/aio/operations/_artifact_stores_operations.py
azure/mgmt/hybridnetwork/aio/operations/_components_operations.py
azure/mgmt/hybridnetwork/aio/operations/_configuration_group_schemas_operations.py
azure/mgmt/hybridnetwork/aio/operations/_configuration_group_values_operations.py
azure/mgmt/hybridnetwork/aio/operations/_network_function_definition_groups_operations.py
azure/mgmt/hybridnetwork/aio/operations/_network_function_definition_versions_operations.py
azure/mgmt/hybridnetwork/aio/operations/_network_functions_operations.py
azure/mgmt/hybridnetwork/aio/operations/_network_service_design_groups_operations.py
azure/mgmt/hybridnetwork/aio/operations/_network_service_design_versions_operations.py
azure/mgmt/hybridnetwork/aio/operations/_operations.py
azure/mgmt/hybridnetwork/aio/operations/_patch.py
azure/mgmt/hybridnetwork/aio/operations/_proxy_artifact_operations.py
azure/mgmt/hybridnetwork/aio/operations/_publishers_operations.py
azure/mgmt/hybridnetwork/aio/operations/_site_network_services_operations.py
azure/mgmt/hybridnetwork/aio/operations/_sites_operations.py
azure/mgmt/hybridnetwork/models/__init__.py
azure/mgmt/hybridnetwork/models/_hybrid_network_management_client_enums.py
azure/mgmt/hybridnetwork/models/_models_py3.py
azure/mgmt/hybridnetwork/models/_patch.py
azure_mgmt_hybridnetwork-2.0.0.dist-info/LICENSE
azure_mgmt_hybridnetwork-2.0.0.dist-info/METADATA
azure_mgmt_hybridnetwork-2.0.0.dist-info/WHEEL
azure_mgmt_hybridnetwork-2.0.0.dist-info/top_level.txt
azure_mgmt_hybridnetwork-2.0.0.dist-info/RECORD
